pyfoamd/__init__.py
pyfoamd/__main__.py
pyfoamd/functions.trash.py
pyfoamd/richinclude.py
pyfoamd/commandline/__init__.py
pyfoamd/commandline/_iPython_env.py
pyfoamd/functions/__init__.py
pyfoamd/functions/allRun.py
pyfoamd/functions/appendEntry.py
pyfoamd/functions/clean.py
pyfoamd/functions/cleanDictFile.py
pyfoamd/functions/cloneCase.py
pyfoamd/functions/cloneCases.py
pyfoamd/functions/extractLogData.py
pyfoamd/functions/foamVersion.py
pyfoamd/functions/getLatestTime.py
pyfoamd/functions/getMonitor.py
pyfoamd/functions/getProbe.py
pyfoamd/functions/init.py
pyfoamd/functions/isCase.py
pyfoamd/functions/isDecomposed.py
pyfoamd/functions/isDictFile.py
pyfoamd/functions/isMeshed.py
pyfoamd/functions/isReconstructed.py
pyfoamd/functions/listCases.py
pyfoamd/functions/load.py
pyfoamd/functions/monitor.old.py
pyfoamd/functions/monitor.py
pyfoamd/functions/parseNameTag.py
pyfoamd/functions/plot.py
pyfoamd/functions/printInputs.py
pyfoamd/functions/readCaseFromCache.py
pyfoamd/functions/readConfig.py
pyfoamd/functions/readDictFile.py
pyfoamd/functions/readInputs.py
pyfoamd/functions/removeBlockEntries.py
pyfoamd/functions/removeEntry.py
pyfoamd/functions/replaceEntry.py
pyfoamd/functions/restore.py
pyfoamd/functions/writeCase.py
pyfoamd/functions/writeConfig.py
pyfoamd/functions/writeParams.py
pyfoamd/richLogger/__init__.py
pyfoamd/types/__init__.py
pyfoamd/types/_isCase.py
pyfoamd/types/_isDictFile.py
pyfoamd/types/_readDictFile.py
pyFoamd-0.1.0.dist-info/LICENSE
pyFoamd-0.1.0.dist-info/METADATA
pyFoamd-0.1.0.dist-info/WHEEL
pyFoamd-0.1.0.dist-info/entry_points.txt
pyFoamd-0.1.0.dist-info/top_level.txt
pyFoamd-0.1.0.dist-info/RECORD
