Metadata-Version: 2.1
Name: pyFoamd
Version: 0.1.0
Summary: Pythonic interface for OpenFOAM dictionaries and case files.
Home-page: https://github.com/mcgoldba/pyFoamd
Author: Marc Goldbach
Author-email: mcgoldba@gmail.com
License: GNU GENERAL PUBLIC LICENSE
Requires-Python: >=3.7
License-File: LICENSE
Requires-Dist: pint
Requires-Dist: pandas
Requires-Dist: rich
